Workbook

Sheet README
B2: ECS Transmission Chain Hypotheses v1
B3: Status: hypotheses, not yet tested · Prepared 2026-10-15 · Scope: ECS (NSCC clearing and DTC settlement, kept separate)
B5: How the logic works
B6: Chain | C6: World event → mechanism → impact on an ECS process. Step 2 (mechanism) is reasoning and is not tested.
B7: Test 1 (Step 1) | C7: Does the signal actually reflect real-world events?
B8: Test 2 (Step 3) | C8: Does the shock reach this business? Judged with the TEST variable, which captures the business reacting.
B9: Vulnerability variable | C9: Used only for scoring. Measures whether the buffer is enough. Never used in Test 2.
B10: Routes and options | C10: A route (R1–R8) is one kind of world event. Where one route has several possible outcomes, each is a separate option (A, B, C). One option per route is marked primary before testing; the others are secondary and are not used for scoring. R3 options A and B are separate risks and both kept.
B12: Before running tests
B13: Freeze | C13: Test methods and pass criteria are proposals. Confirm as a team and freeze before running. If a change is needed, record why and bump the version.
B14: One test per chain | C14: Test only the one signal and one test variable on each row. No extra comparisons.
B15: Prior results | C15: 'Prior results seen?' flags pairs the team already looked at. Those results are exploratory, not confirmations.
B17: Confidence rules (filled in automatically on the Chains tab)
B18: High | C18: Test 1 and Test 2 both pass
B19: Medium | C19: Test 1 passes, Test 2 inconclusive due to limited data
B20: Low/Medium | C20: Chains without a market indicator, supported by logic and cases
B21: Revise or drop | C21: Test 1 fails, or Test 2 is significant in the wrong direction
B23: Data status labels
B24: Have | C24: Already in the project database; ready to use
B25: Partial | C25: Partly available, or needs checking first
B26: Missing | C26: Not yet available; needs collecting or extracting
B27: N/A | C27: No data needed (uses the scoring rubric)
B29: What to edit
B30: Yellow cells | C30: On the Chains tab, the Test record columns (Test 1 result, Test 2 result, date, tester, notes) are for the tester. Confidence and Ready to run update by formula.
B31: Ready to run? | C31: Looks only at the signal and the test variable, since those are all the two tests need. The vulnerability variable is needed later, for scoring.
B32: Everything else | C32: Change only with team agreement, then bump the version.
B34: Tabs
B35: Chains | C35: One row per chain: the full hypothesis, test plan and test record. Machine-readable; a matching CSV is saved next to this file.
B36: Summary | C36: Counts by status, ready-to-run, and confidence. Updates by formula.
B37: ECS Signals | C37: Candidate ECS-specific signals, marked leading vs. coincident, and whether they're in the database.
B38: Prior Results | C38: What the team's earlier runs already showed for NSCC (Oct 6 tests).
B39: Data Gaps | C39: What to collect or extract before each chain can run, ordered by effort.
B40: Open Questions | C40: Decisions the team still needs to make.

Sheet Summary
B2: Summary
B3: All counts update from the Chains tab.
B5: Overview | C5: Count
B6: Total chains | C6: =COUNTA(Chains!$A$3:$A$16) -> 14
B7: NSCC chains | C7: =COUNTIF(Chains!$E$3:$E$16,"NSCC") -> 9
B8: DTC chains | C8: =COUNTIF(Chains!$E$3:$E$16,"DTC") -> 5
B9: With market indicator | C9: =COUNTIF(Chains!$F$3:$F$16,"With market indicator") -> 11
B10: Without market indicator | C10: =COUNTIF(Chains!$F$3:$F$16,"Without market indicator") -> 3
B11: Core priority | C11: =COUNTIF(Chains!$H$3:$H$16,"Core") -> 6
B12: Extension priority | C12: =COUNTIF(Chains!$H$3:$H$16,"Extension") -> 8
B14: Ready to run? | C14: Count
B15: Yes | C15: =COUNTIF(Chains!$AB$3:$AB$16,"Yes") -> 4
B16: After checks | C16: =COUNTIF(Chains!$AB$3:$AB$16,"After checks") -> 2
B17: Not yet (signal or test data missing) | C17: =COUNTIF(Chains!$AB$3:$AB$16,"No*") -> 8
B19: Test results | C19: PASS | D19: FAIL | E19: Other | F19: Not run
B20: Test 1 | C20: =COUNTIF(Chains!$AC$3:$AC$16,"PASS") -> 0 | D20: =COUNTIF(Chains!$AC$3:$AC$16,"FAIL") -> 0 | E20: =COUNTA(Chains!$AC$3:$AC$16)-C20-D20 -> 0 | F20: =COUNTA(Chains!$A$3:$A$16)-COUNTA(Chains!$AC$3:$AC$16) -> 14
B21: Test 2 | C21: =COUNTIF(Chains!$AD$3:$AD$16,"PASS") -> 0 | D21: =COUNTIF(Chains!$AD$3:$AD$16,"FAIL") -> 0 | E21: =COUNTA(Chains!$AD$3:$AD$16)-C21-D21 -> 0 | F21: =COUNTA(Chains!$A$3:$A$16)-COUNTA(Chains!$AD$3:$AD$16) -> 14
B23: Confidence | C23: Count
B24: High | C24: =COUNTIF(Chains!$AE$3:$AE$16,"High") -> 0
B25: Medium | C25: =COUNTIF(Chains!$AE$3:$AE$16,"Medium") -> 0
B26: Low/Medium | C26: =COUNTIF(Chains!$AE$3:$AE$16,"Low/Medium") -> 0
B27: Revise or drop | C27: =COUNTIF(Chains!$AE$3:$AE$16,"Revise or drop") -> 0
B29: Data status (all variables) | C29: Have | D29: Partial | E29: Missing | F29: N/A
B30: Signal / test / vulnerability | C30: =COUNTIF(Chains!$L$3:$L$16,"Have")+COUNTIF(Chains!$Q$3:$Q$16,"Have")+COUNTIF(Chains!$U$3:$U$16,"Have") -> 17 | D30: =COUNTIF(Chains!$L$3:$L$16,"Partial")+COUNTIF(Chains!$Q$3:$Q$16,"Partial")+COUNTIF(Chains!$U$3:$U$16,"Partial") -> 2 | E30: =COUNTIF(Chains!$L$3:$L$16,"Missing")+COUNTIF(Chains!$Q$3:$Q$16,"Missing")+COUNTIF(Chains!$U$3:$U$16,"Missing") -> 20 | F30: =COUNTIF(Chains!$L$3:$L$16,"N/A")+COUNTIF(Chains!$Q$3:$Q$16,"N/A")+COUNTIF(Chains!$U$3:$U$16,"N/A") -> 3

Sheet Chains
A1: CHAIN | I1: STEP 1 · SIGNAL | M1: STEP 2 | N1: STEP 3 · BUSINESS IMPACT | V1: TEST PLAN (freeze before running) | AB1: TEST RECORD (fill in after running)
A2: ID | B2: Route | C2: Option | D2: Chain name | E2: Sub-business | F2: Type | G2: Risk family | H2: Priority | I2: Step 1 · World event | J2: Step 1 · Signal | K2: Signal source | L2: Signal data | M2: Step 2 · Mechanism (not tested) | N2: Step 3 · Process touched | O2: Step 3 · Test variable (business reacting) | P2: Test variable source / field | Q2: Test var data | R2: Step 3 · Vulnerability variable (buffer, scoring only) | S2: Vulnerability source / field | T2: Direction | U2: Vuln data | V2: Historical event windows | W2: Prior results seen? | X2: Test 1 · method & pass criteria (proposed) | Y2: Test 2 · method & pass criteria (proposed) | Z2: Key unknowns | AA2: Notes / overlap | AB2: Ready to run? | AC2: Test 1 result | AD2: Test 2 result | AE2: Confidence | AF2: Test date | AG2: Tester | AH2: Result notes
A3: ECS-NSCC-01A | B3: R1 Equity selloff | C3: A (primary) | D3: Equity selloff → margin calls | E3: NSCC | F3: With market indicator | G3: Market | H3: Core | I3: Sharp stock selloff; equity prices swing hard over days | J3: VIX, weekly peak (backup: S&P 500 largest daily move) | K3: FRED VIXCLS (backup: FRED SP500) | L3: Have | M3: Prices swing → NSCC's margin model recalculates → members get larger margin (Clearing Fund) calls | N3: NSCC Clearing Fund (margin) calls | O3: Margin call vs prior-quarter margin | P3: pqd_quarterly: im_call_to_prior_im (NSCC) | Q3: Have | R3: Cover-1 stress loss ÷ margin | S3: pqd_quarterly: stress_loss_to_im (PQD 4.4.3 ÷ 6.1.1) | T3: Higher = more vulnerable | U3: Have | V3: 2020-03-09 to 03-23: COVID shock 2021-01-25 to 01-29: meme-stock week (GameStop) 2024-08-05 to 08-09: volatility spike (yen carry unwind) 2025-04-02 to 04-11: tariff market shock | W3: Yes (exploratory, post-result): VIX vs im_call_to_prior_im rho 0.19 (n=22). VIX failed Test 1 (hit 1/2 events). New signal (S&P 500 returns) not yet seen. | X3: Alert when the weekly peak is above the 90th percentile of the prior 52 weeks (excluding the current week). Pass if alerts hit ≥ 2/3 of event windows and the alert rate outside events is ≤ 15%. (Team standard) | Y3: Quarterly max of the weekly signal vs the same-quarter test variable. Pass if Spearman rho ≥ 0.3 and the 4-quarter block-bootstrap 95% CI lower bound > 0. (Team standard) | Z3: Quarterly PQD only (~23 quarters); margin also moves with business growth and model changes | AA3: Primary for R1, chosen before testing. 01B and 01C are secondary and not used for scoring. | AB3: =IF(COUNTIF(L3,"Missing")+COUNTIF(Q3,"Missing")>0,"No: "&(COUNTIF(L3,"Missing")+COUNTIF(Q3,"Missing"))&" missing",IF(COUNTIF(L3,"Partial")+COUNTIF(Q3,"Partial")>0,"After checks","Yes")) -> Yes | AE3: =IF(OR(AC3="",AD3=""),"",IF(OR(AC3="FAIL",AD3="WRONG DIRECTION"),"Revise or drop",IF(F3="Without market indicator","Low/Medium",IF(AND(AC3="PASS",AD3="PASS"),"High",IF(AND(AC3="PASS",AD3="INCONCLUSIVE"),"Medium","Low/Medium")))))
A4: ECS-NSCC-01B | B4: R1 Equity selloff | C4: B | D4: Equity selloff → variation margin cash swings | E4: NSCC | F4: With market indicator | G4: Liquidity | H4: Extension | I4: Sharp stock selloff; equity prices swing hard over days | J4: VIX, weekly peak (backup: S&P 500 largest daily move) | K4: FRED VIXCLS (backup: FRED SP500) | L4: Have | M4: Prices swing → daily mark-to-market payments jump → members must move more cash the same day → NSCC's settlement cash needs rise | N4: NSCC daily variation margin and settlement cash flows | O4: Peak single-day VM ÷ average VM | P4: pqd_quarterly: vm_peak_to_avg (PQD 6.7.x) | Q4: Have | R4: Largest payment obligation ÷ qualifying liquid resources | S4: pqd_quarterly: payment_to_qlr (PQD 7.3.4 ÷ 7.1) | T4: Higher = more vulnerable | U4: Have | V4: 2020-03-09 to 03-23: COVID shock 2021-01-25 to 01-29: meme-stock week (GameStop) 2024-08-05 to 08-09: volatility spike (yen carry unwind) 2025-04-02 to 04-11: tariff market shock | W4: Yes (exploratory): VIX vs vm_peak_to_avg rho 0.08; VIX vs vm_peak_usd rho 0.33. SOFR−EFFR adj. vs vm_peak_to_avg rho 0.55. | X4: Alert when the weekly peak is above the 90th percentile of the prior 52 weeks (excluding the current week). Pass if alerts hit ≥ 2/3 of event windows and the alert rate outside events is ≤ 15%. (Team standard) | Y4: Quarterly max of the weekly signal vs the same-quarter test variable. Pass if Spearman rho ≥ 0.3 and the 4-quarter block-bootstrap 95% CI lower bound > 0. (Team standard) | Z4: Member-level cash positions not public | AA4: Secondary to 01A. Shares its vulnerability variable with 03B. | AB4: =IF(COUNTIF(L4,"Missing")+COUNTIF(Q4,"Missing")>0,"No: "&(COUNTIF(L4,"Missing")+COUNTIF(Q4,"Missing"))&" missing",IF(COUNTIF(L4,"Partial")+COUNTIF(Q4,"Partial")>0,"After checks","Yes")) -> Yes | AE4: =IF(OR(AC4="",AD4=""),"",IF(OR(AC4="FAIL",AD4="WRONG DIRECTION"),"Revise or drop",IF(F4="Without market indicator","Low/Medium",IF(AND(AC4="PASS",AD4="PASS"),"High",IF(AND(AC4="PASS",AD4="INCONCLUSIVE"),"Medium","Low/Medium")))))
A5: ECS-NSCC-01C | B5: R1 Equity selloff | C5: C | D5: Equity selloff → margin model misses | E5: NSCC | F5: With market indicator | G5: Credit | H5: Extension | I5: Sharp stock selloff; equity prices swing hard over days | J5: VIX, weekly peak (backup: S&P 500 largest daily move) | K5: FRED VIXCLS (backup: FRED SP500) | L5: Have | M5: Moves exceed what the margin model expected → margin falls short on more days → NSCC is briefly under-collateralized | N5: NSCC margin model coverage (backtesting) | O5: Number of margin backtest breaches | P5: pqd_quarterly: backtest_breaches (NSCC) | Q5: Have | R5: Largest uncovered amount ÷ margin | S5: pqd_quarterly: backtest_uncovered_peak_to_im | T5: Higher = more vulnerable | U5: Have | V5: 2020-03-09 to 03-23: COVID shock 2021-01-25 to 01-29: meme-stock week (GameStop) 2024-08-05 to 08-09: volatility spike (yen carry unwind) 2025-04-02 to 04-11: tariff market shock | W5: Not tested on this pair. VIX failed Test 1. | X5: Alert when the weekly peak is above the 90th percentile of the prior 52 weeks (excluding the current week). Pass if alerts hit ≥ 2/3 of event windows and the alert rate outside events is ≤ 15%. (Team standard) | Y5: Quarterly max of the weekly signal vs the same-quarter test variable. Pass if Spearman rho ≥ 0.3 and the 4-quarter block-bootstrap 95% CI lower bound > 0. (Team standard) | Z5: Breach counts depend on NSCC model changes, not only market moves | AA5: Secondary to 01A. | AB5: =IF(COUNTIF(L5,"Missing")+COUNTIF(Q5,"Missing")>0,"No: "&(COUNTIF(L5,"Missing")+COUNTIF(Q5,"Missing"))&" missing",IF(COUNTIF(L5,"Partial")+COUNTIF(Q5,"Partial")>0,"After checks","Yes")) -> Yes | AE5: =IF(OR(AC5="",AD5=""),"",IF(OR(AC5="FAIL",AD5="WRONG DIRECTION"),"Revise or drop",IF(F5="Without market indicator","Low/Medium",IF(AND(AC5="PASS",AD5="PASS"),"High",IF(AND(AC5="PASS",AD5="INCONCLUSIVE"),"Medium","Low/Medium")))))
A6: ECS-NSCC-02A | B6: R2 Trading volume surge | C6: A (primary) | D6: Volume surge → settlement fails | E6: NSCC | F6: With market indicator | G6: Operational | H6: Core | I6: Record trading days (meme-stock rally, panic selling, index events) | J6: US consolidated equity volume, weekly peak | K6: Cboe U.S. Equities Market Volume Summary (daily) | L6: Missing | M6: Trade count surges → more trades can't be delivered on time → NSCC's settlement fails rise | N6: NSCC Continuous Net Settlement (CNS) deliveries | O6: Aggregate fails-to-deliver | P6: SEC Fails-to-Deliver data (from NSCC CNS; twice monthly, daily values) | Q6: Missing | R6: TBD (no public capacity-buffer field) | S6: TBD | T6: — | U6: Missing | V6: 2020-03-09 to 03-23: COVID shock 2021-01-25 to 01-29: meme-stock week 2025-04-02 to 04-11: tariff market shock | W6: No | X6: Alert when the weekly peak is above the 90th percentile of the prior 52 weeks (excluding the current week). Pass if alerts hit ≥ 2/3 of event windows and the alert rate outside events is ≤ 15%. (Team standard) | Y6: Event study: shock weeks = signal above the 90th percentile of the prior 52 weeks. Regress the weekly test variable on a shock-week dummy plus month-end and quarter-end dummies. Pass if the coefficient > 0 with p < 0.05 (HAC standard errors). | Z6: Fails also driven by short selling and securities lending, not only volume | AA6: Scores Shock only until a vulnerability field is found. | AB6: =IF(COUNTIF(L6,"Missing")+COUNTIF(Q6,"Missing")>0,"No: "&(COUNTIF(L6,"Missing")+COUNTIF(Q6,"Missing"))&" missing",IF(COUNTIF(L6,"Partial")+COUNTIF(Q6,"Partial")>0,"After checks","Yes")) -> No: 2 missing | AE6: =IF(OR(AC6="",AD6=""),"",IF(OR(AC6="FAIL",AD6="WRONG DIRECTION"),"Revise or drop",IF(F6="Without market indicator","Low/Medium",IF(AND(AC6="PASS",AD6="PASS"),"High",IF(AND(AC6="PASS",AD6="INCONCLUSIVE"),"Medium","Low/Medium")))))
A7: ECS-NSCC-02B | B7: R2 Trading volume surge | C7: B | D7: Volume surge → system strain | E7: NSCC | F7: With market indicator | G7: Operational | H7: Extension | I7: Record trading days (meme-stock rally, panic selling, index events) | J7: US consolidated equity volume, weekly peak | K7: Cboe U.S. Equities Market Volume Summary (daily) | L7: Missing | M7: Trade count surges → trade capture and netting run near peak load → slowdowns or outages | N7: NSCC trade capture and netting systems | O7: Number and duration of operational failures | P7: PQD 17.3 (extract from existing PQD files) | Q7: Missing | R7: Core-system availability | S7: PQD 17.2 (extract from existing PQD files) | T7: Lower = more vulnerable | U7: Missing | V7: 2021-01-25 to 01-29: meme-stock week 2025-04-02 to 04-11: tariff market shock | W7: No | X7: Alert when the weekly peak is above the 90th percentile of the prior 52 weeks (excluding the current week). Pass if alerts hit ≥ 2/3 of event windows and the alert rate outside events is ≤ 15%. (Team standard) | Y7: Quarterly max of the weekly signal vs the same-quarter test variable. Pass if Spearman rho ≥ 0.3 and the 4-quarter block-bootstrap 95% CI lower bound > 0. (Team standard) | Z7: 17.x may be DTCC-wide, not NSCC-only; failures are rare, so few non-zero quarters | AA7: Same signal as 02A; keep one for scoring. | AB7: =IF(COUNTIF(L7,"Missing")+COUNTIF(Q7,"Missing")>0,"No: "&(COUNTIF(L7,"Missing")+COUNTIF(Q7,"Missing"))&" missing",IF(COUNTIF(L7,"Partial")+COUNTIF(Q7,"Partial")>0,"After checks","Yes")) -> No: 2 missing | AE7: =IF(OR(AC7="",AD7=""),"",IF(OR(AC7="FAIL",AD7="WRONG DIRECTION"),"Revise or drop",IF(F7="Without market indicator","Low/Medium",IF(AND(AC7="PASS",AD7="PASS"),"High",IF(AND(AC7="PASS",AD7="INCONCLUSIVE"),"Medium","Low/Medium")))))
A8: ECS-NSCC-03A | B8: R3 Broker / member stress | C8: A | D8: Broker distress → default exposure | E8: NSCC | F8: With market indicator | G8: Credit | H8: Core | I8: A broker-dealer or bank is downgraded, reports big losses, or fails | J8: 20-day widening in the Baa credit spread, weekly peak | K8: FRED BAA10Y (in database as baa_widen20) | L8: Have | M8: Credit conditions worsen → a member is more likely to default → NSCC uses default resources and other members share losses | N8: NSCC default management and mutualized Clearing Fund | O8: Historical case evidence | P8: e.g. Jan 2021: brokers faced large NSCC deposit calls during the meme-stock week (verify original sources) | Q8: Missing | R8: Top-5 members' share of open positions | S8: pqd_quarterly: top5_open_share (PQD 18.2.2) | T8: Higher = more vulnerable | U8: Have | V8: 2020-03-09 to 03-23: COVID shock 2021-01-25 to 01-29: meme-stock week 2023-03-08 to 03-17: bank stress (SVB) | W8: Yes for the signal: baa_widen20 PASSED Test 1 (Oct 6 event screen). | X8: Original Test 1 already passed; re-run once with weekly peaks to confirm | Y8: Pass if at least 1 past event has public evidence that NSCC default management or member risk measures was affected. Expected confidence: Low/Medium. | Z8: Which members are under strain is not public | AA8: Same signal as FICC-GSD-04; news is tagged per business line. | AB8: =IF(COUNTIF(L8,"Missing")+COUNTIF(Q8,"Missing")>0,"No: "&(COUNTIF(L8,"Missing")+COUNTIF(Q8,"Missing"))&" missing",IF(COUNTIF(L8,"Partial")+COUNTIF(Q8,"Partial")>0,"After checks","Yes")) -> No: 1 missing | AE8: =IF(OR(AC8="",AD8=""),"",IF(OR(AC8="FAIL",AD8="WRONG DIRECTION"),"Revise or drop",IF(F8="Without market indicator","Low/Medium",IF(AND(AC8="PASS",AD8="PASS"),"High",IF(AND(AC8="PASS",AD8="INCONCLUSIVE"),"Medium","Low/Medium")))))
A9: ECS-NSCC-03B | B9: R3 Broker / member stress | C9: B | D9: Funding squeeze → member can't meet NSCC payments | E9: NSCC | F9: With market indicator | G9: Liquidity | H9: Core | I9: Short-term funding markets tighten; brokers struggle to raise cash | J9: SOFR − EFFR, quarter-end adjusted, weekly peak | K9: FRED SOFR, EFFR (in database as sofr_effr_adjusted) | L9: Have | M9: Funding gets expensive → brokers have less cash on hand → margin and settlement payments to NSCC get harder to meet → NSCC's liquidity needs rise | N9: NSCC daily settlement payments and liquidity | O9: Margin call ÷ margin | P9: pqd_quarterly: im_call_to_im (NSCC) | Q9: Have | R9: Largest payment obligation ÷ qualifying liquid resources | S9: pqd_quarterly: payment_to_qlr (PQD 7.3.4 ÷ 7.1) | T9: Higher = more vulnerable | U9: Have | V9: 2019-09-16 to 09-20: repo spike (before PQD history) 2020-03-09 to 03-23: COVID shock 2025-04-02 to 04-11: tariff market shock | W9: Yes: signal PASSED Test 1. Exploratory: vs im_call_to_im rho 0.45 (n=23), seen before writing. | X9: Original Test 1 already passed; re-run once with weekly peaks to confirm | Y9: Quarterly max of the weekly signal vs the same-quarter test variable. Pass if Spearman rho ≥ 0.3 and the 4-quarter block-bootstrap 95% CI lower bound > 0. (Team standard) | Z9: Member funding positions not public; NSCC payment_to_core_qlr equals payment_to_qlr in the data | AA9: Shares vulnerability with 01B. Prior result seen, so treat Test 2 as confirmatory only. | AB9: =IF(COUNTIF(L9,"Missing")+COUNTIF(Q9,"Missing")>0,"No: "&(COUNTIF(L9,"Missing")+COUNTIF(Q9,"Missing"))&" missing",IF(COUNTIF(L9,"Partial")+COUNTIF(Q9,"Partial")>0,"After checks","Yes")) -> Yes | AE9: =IF(OR(AC9="",AD9=""),"",IF(OR(AC9="FAIL",AD9="WRONG DIRECTION"),"Revise or drop",IF(F9="Without market indicator","Low/Medium",IF(AND(AC9="PASS",AD9="PASS"),"High",IF(AND(AC9="PASS",AD9="INCONCLUSIVE"),"Medium","Low/Medium")))))
A10: ECS-NSCC-04 | B10: R4 Settlement cycle change | C10: — | D10: T+1 / T+0 / 24x5 → NSCC fails | E10: NSCC | F10: Without market indicator | G10: Regulatory | H10: Core | I10: SEC or industry moves to a shorter settlement cycle or longer trading hours | J10: None; use the scoring rubric (certainty, scope, time to event) | K10: N/A | L10: N/A | M10: Less time between trade and settlement → late or manual steps become the bottleneck → more trades fail at NSCC | N10: Settling NSCC-cleared trades on time | O10: NSCC fail rate (monthly) | P10: DTCC Equities by the Numbers (data_refresh: May-2024 and Aug-2026 only) | Q10: Partial | R10: TBD | S10: TBD (candidate: industry affirmation rate, ITP data, not PQD) | T10: — | U10: Missing | V10: 2023-02-15: SEC adopts T+1 2024-05-28: US T+1 go-live 24x5 / T+0 milestones (to compile) | W10: Partial look: NSCC fail rate 2.00% (May 2024) → 2.21% (Aug 2026). | X10: No statistical test. Confirm each event or milestone has a named public source (rule text, press release, official notice). | Y10: Compare the monthly fail rate for the 3 months after each milestone vs the 3 months before. Pass if higher after (direction fixed before running). | Z10: Monthly history before 2024 not yet collected; fails also move with market activity | AA10: Split from ECS-DTC-01 so NSCC and DTC stay separate. | AB10: =IF(COUNTIF(L10,"Missing")+COUNTIF(Q10,"Missing")>0,"No: "&(COUNTIF(L10,"Missing")+COUNTIF(Q10,"Missing"))&" missing",IF(COUNTIF(L10,"Partial")+COUNTIF(Q10,"Partial")>0,"After checks","Yes")) -> After checks | AE10: =IF(OR(AC10="",AD10=""),"",IF(OR(AC10="FAIL",AD10="WRONG DIRECTION"),"Revise or drop",IF(F10="Without market indicator","Low/Medium",IF(AND(AC10="PASS",AD10="PASS"),"High",IF(AND(AC10="PASS",AD10="INCONCLUSIVE"),"Medium","Low/Medium")))))
A11: ECS-NSCC-05 | B11: R5 Scheduled peak days | C11: — | D11: Known peak dates → processing load | E11: NSCC | F11: Without market indicator | G11: Operational | H11: Extension | I11: Triple witching, Russell reconstitution, S&P quarterly rebalance | J11: None; use the scoring rubric (dates known in advance) | K11: N/A | L11: N/A | M11: Activity bunches onto one known date → a predictable volume peak → NSCC runs at high load that session | N11: NSCC processing on known peak dates | O11: Fails-to-deliver in the week after each peak date | P11: SEC Fails-to-Deliver data | Q11: Missing | R11: TBD | S11: TBD | T11: — | U11: Missing | V11: Quarterly triple-witching Fridays 2018–now Annual Russell reconstitution (late June) S&P quarterly rebalances | W11: No | X11: No statistical test. Confirm each event or milestone has a named public source (rule text, press release, official notice). | Y11: Event study: shock weeks = weeks containing a scheduled peak date. Regress the weekly test variable on a shock-week dummy plus month-end and quarter-end dummies. Pass if the coefficient > 0 with p < 0.05 (HAC standard errors). | Z11: Peak-day capacity plans not public | AA11: Forward-looking: feeds the upcoming-events view. Shares test data with 02A. | AB11: =IF(COUNTIF(L11,"Missing")+COUNTIF(Q11,"Missing")>0,"No: "&(COUNTIF(L11,"Missing")+COUNTIF(Q11,"Missing"))&" missing",IF(COUNTIF(L11,"Partial")+COUNTIF(Q11,"Partial")>0,"After checks","Yes")) -> No: 1 missing | AE11: =IF(OR(AC11="",AD11=""),"",IF(OR(AC11="FAIL",AD11="WRONG DIRECTION"),"Revise or drop",IF(F11="Without market indicator","Low/Medium",IF(AND(AC11="PASS",AD11="PASS"),"High",IF(AND(AC11="PASS",AD11="INCONCLUSIVE"),"Medium","Low/Medium")))))
A12: ECS-DTC-01 | B12: R4 Settlement cycle change | C12: — | D12: T+1 / T+0 / 24x5 → DTC fails | E12: DTC | F12: Without market indicator | G12: Regulatory | H12: Core | I12: SEC or industry moves to a shorter settlement cycle or longer trading hours | J12: None; use the scoring rubric (certainty, scope, time to event) | K12: N/A | L12: N/A | M12: Less time to settle → more deliveries miss the DTC cutoff → DTC fails and recycling rise | N12: DTC end-of-day settlement completion | O12: DTC fail rate (monthly) | P12: DTCC Equities by the Numbers (data_refresh: May-2024 and Aug-2026 only) | Q12: Partial | R12: TBD (DTC has no PQD) | S12: TBD | T12: — | U12: Missing | V12: 2023-02-15: SEC adopts T+1 2024-05-28: US T+1 go-live | W12: Partial look: DTC fail rate 2.83% (May 2024) → 3.18% (Aug 2026). | X12: No statistical test. Confirm each event or milestone has a named public source (rule text, press release, official notice). | Y12: Compare the monthly fail rate for the 3 months after each milestone vs the 3 months before. Pass if higher after (direction fixed before running). | Z12: Monthly history before 2024 not yet collected | AA12: DTC side of R4. | AB12: =IF(COUNTIF(L12,"Missing")+COUNTIF(Q12,"Missing")>0,"No: "&(COUNTIF(L12,"Missing")+COUNTIF(Q12,"Missing"))&" missing",IF(COUNTIF(L12,"Partial")+COUNTIF(Q12,"Partial")>0,"After checks","Yes")) -> After checks | AE12: =IF(OR(AC12="",AD12=""),"",IF(OR(AC12="FAIL",AD12="WRONG DIRECTION"),"Revise or drop",IF(F12="Without market indicator","Low/Medium",IF(AND(AC12="PASS",AD12="PASS"),"High",IF(AND(AC12="PASS",AD12="INCONCLUSIVE"),"Medium","Low/Medium")))))
A13: ECS-DTC-02A | B13: R6 Technology threat | C13: A (primary) | D13: New exploited vulnerabilities → DTC disruption | E13: DTC | F13: With market indicator | G13: Cyber | H13: Extension | I13: A widely used software flaw is actively exploited; a cyberattack hits a market firm | J13: New CISA Known-Exploited-Vulnerabilities entries, weekly count | K13: CISA KEV catalog (in repo: cisa_catalog_entries.csv) | L13: Have | M13: Exploited flaw hits DTC, a participant or a vendor → a system goes down → deliveries stall → settlement runs late | N13: DTC end-of-day settlement completion | O13: DTCC public service notices (outages, extended cutoffs) | P13: DTCC Important Notices (to collect) | Q13: Missing | R13: TBD (DTC has no PQD) | S13: TBD | T13: — | U13: Missing | V13: 2023-11: ICBC US ransomware (Treasury settlement disruption; check for any DTC impact) 2024-07-19: global IT outage (check for any DTC impact) | W13: No | X13: Alert when the weekly peak is above the 90th percentile of the prior 52 weeks (excluding the current week). Pass if alerts hit ≥ 2/3 of event windows and the alert rate outside events is ≤ 15%. (Team standard) | Y13: Pass if at least 1 past event has public evidence that DTC settlement or service availability was affected. Expected confidence: Low/Medium. | Z13: Most incidents inside firms are never made public | AA13: KEV is broad; most entries won't touch DTC. Option B uses cloud incidents instead. | AB13: =IF(COUNTIF(L13,"Missing")+COUNTIF(Q13,"Missing")>0,"No: "&(COUNTIF(L13,"Missing")+COUNTIF(Q13,"Missing"))&" missing",IF(COUNTIF(L13,"Partial")+COUNTIF(Q13,"Partial")>0,"After checks","Yes")) -> No: 1 missing | AE13: =IF(OR(AC13="",AD13=""),"",IF(OR(AC13="FAIL",AD13="WRONG DIRECTION"),"Revise or drop",IF(F13="Without market indicator","Low/Medium",IF(AND(AC13="PASS",AD13="PASS"),"High",IF(AND(AC13="PASS",AD13="INCONCLUSIVE"),"Medium","Low/Medium")))))
A14: ECS-DTC-02B | B14: R6 Technology threat | C14: B | D14: Cloud / vendor outage → DTC disruption | E14: DTC | F14: With market indicator | G14: Operational | H14: Extension | I14: A major cloud or network provider has a widespread outage | J14: Weekly count and duration of major cloud-provider incidents | K14: Provider status pages (in repo: provider_product_incidents.csv) | L14: Have | M14: A shared vendor goes down → DTC or its participants lose a dependency → deliveries stall → settlement runs late | N14: DTC end-of-day settlement completion | O14: DTCC public service notices (outages, extended cutoffs) | P14: DTCC Important Notices (to collect) | Q14: Missing | R14: TBD (DTC has no PQD) | S14: TBD | T14: — | U14: Missing | V14: 2024-07-19: global IT outage (check for any DTC impact) | W14: No | X14: Alert when the weekly peak is above the 90th percentile of the prior 52 weeks (excluding the current week). Pass if alerts hit ≥ 2/3 of event windows and the alert rate outside events is ≤ 15%. (Team standard) | Y14: Pass if at least 1 past event has public evidence that DTC settlement or service availability was affected. Expected confidence: Low/Medium. | Z14: Which vendors DTC uses is not public | AA14: Alternative to 02A; same test variable. | AB14: =IF(COUNTIF(L14,"Missing")+COUNTIF(Q14,"Missing")>0,"No: "&(COUNTIF(L14,"Missing")+COUNTIF(Q14,"Missing"))&" missing",IF(COUNTIF(L14,"Partial")+COUNTIF(Q14,"Partial")>0,"After checks","Yes")) -> No: 1 missing | AE14: =IF(OR(AC14="",AD14=""),"",IF(OR(AC14="FAIL",AD14="WRONG DIRECTION"),"Revise or drop",IF(F14="Without market indicator","Low/Medium",IF(AND(AC14="PASS",AD14="PASS"),"High",IF(AND(AC14="PASS",AD14="INCONCLUSIVE"),"Medium","Low/Medium")))))
... A16: ECS-DTC-04 | B16: R8 Bank funding stress | C16: — | D16: Funding stress → DTC end-of-day money settlement | E16: DTC | F16: With market indicator | G16: Liquidity | H16: Extension | I16: Short-term bank funding markets tighten | J16: Financial commercial paper − T-bill spread, weekly peak | K16: FRED DCPF3M − DTB3 | L16: Missing | M16: Banks find cash harder to get → participants slower to fund end-of-day balances → DTC must cover any gap with its own liquidity | N16: DTC end-of-day money settlement | O16: Historical case evidence | P16: e.g. March 2020 settlement pressure (to research) | Q16: Missing | R16: TBD (DTC has no PQD) | S16: TBD (candidate: Participants Fund / liquidity resources from DTC quarterly financial statements already in the repo) | T16: — | U16: Missing | V16: 2020-03-09 to 03-23: COVID shock 2023-03-08 to 03-17: bank stress (SVB) | W16: No | X16: Alert when the weekly peak is above the 90th percentile of the prior 52 weeks (excluding the current week). Pass if alerts hit ≥ 2/3 of event windows and the alert rate outside events is ≤ 15%. (Team standard) | Y16: Pass if at least 1 past event has public evidence that DTC end-of-day money settlement was affected. Expected confidence: Low/Medium. | Z16: Participant-level balances not public | AA16: DTC side of funding stress (NSCC side is 03B). | AB16: =IF(COUNTIF(L16,"Missing")+COUNTIF(Q16,"Missing")>0,"No: "&(COUNTIF(L16,"Missing")+COUNTIF(Q16,"Missing"))&" missing",IF(COUNTIF(L16,"Partial")+COUNTIF(Q16,"Partial")>0,"After checks","Yes")) -> No: 2 missing | AE16: =IF(OR(AC16="",AD16=""),"",IF(OR(AC16="FAIL",AD16="WRONG DIRECTION"),"Revise or drop",IF(F16="Without market indicator","Low/Medium",IF(AND(AC16="PASS",AD16="PASS"),"High",IF(AND(AC16="PASS",AD16="INCONCLUSIVE"),"Medium","Low/Medium")))))

Sheet ECS Signals
A1: Signal | B1: What it captures | C1: Timing | D1: Frequency | E1: Source / ID | F1: In database? | G1: Used by | H1: Notes
A2: S&P 500 largest absolute daily return (weekly peak) | B2: Size of equity price shocks | C2: Coincident | D2: Daily | E2: FRED SP500 | F2: Partial (2025-09 on) | G2: R1 (01A/B/C) | H2: Proposed main ECS shock signal. Backfill to 2018.
A3: S&P 500 20-day realized volatility | B3: How choppy the market has been | C3: Coincident / lagging | D3: Daily | E3: Computed from FRED SP500 | F3: Partial | G3: Backup for R1 | H3: Smoother than daily returns; reacts later.
A4: VIX | B4: Expected 30-day equity volatility | C4: Coincident | D4: Daily | E4: FRED VIXCLS | F4: Have (2018 on) | G4: Backup for R1 | H4: Failed Test 1 on Oct 6 (hit 1 of 2 events). Spikes with the event, so little early warning.
A5: VIX above 3-month VIX (term-structure inversion) | B5: Acute stress: near-term fear above longer-term | C5: Coincident | D5: Daily | E5: FRED VIXCLS and VXVCLS (verify ID) | F5: Partial | G5: Option for R1 | H5: Flags panics more sharply than VIX level.
A6: US consolidated equity volume (weekly peak) | B6: Trading activity surges | C6: Coincident | D6: Daily | E6: Cboe U.S. Equities Market Volume Summary | F6: Missing | G6: R2 (02A/B) | H6: Closest public proxy for NSCC load.
A7: Listed options volume | B7: Options activity; peaks at expirations | C7: Coincident | D7: Daily | E7: OCC daily volume statistics | F7: Missing | G7: Option for R2/R5 | H7: Useful around triple-witching dates.
A8: FINRA margin debt | B8: Leverage building up in customer accounts | C8: Leading | D8: Monthly | E8: FINRA Margin Statistics | F8: Missing | G8: Option for R1/R3 | H8: Early warning: high leverage → bigger margin calls when prices drop.
A9: FINRA short interest | B9: Crowded short positions | C9: Leading | D9: Twice monthly | E9: FINRA Equity Short Interest | F9: Missing | G9: Option for R2 | H9: Early warning for squeeze episodes like Jan 2021.
A10: ETF net issuance | B10: Creation/redemption pressure | C10: Coincident | D10: Weekly | E10: ICI weekly ETF estimates | F10: Missing | G10: Future ETF chain | H10: ETF reference list already in repo, but not flows.
A11: Scheduled peak calendar | B11: Known high-volume dates | C11: Forward-known | D11: Event | E11: Exchange and index provider calendars | F11: Missing | G11: R5 (NSCC-05) | H11: Only true forward-looking signal; feeds the upcoming-events view.
A12: Baa credit spread, 20-day widening | B12: Credit stress at firms | C12: Coincident | D12: Daily | E12: FRED BAA10Y (baa_widen20) | F12: Have | G12: R3 (03A) | H12: Passed Test 1 on Oct 6.
... A17: SEC fails-to-deliver | B17: Settlement failures at NSCC | C17: Lagging | D17: Daily (published twice monthly) | E17: SEC FTD data | F17: Missing | G17: Test variable for R2/R5 | H17: Better as a test variable (business reacting) than a signal.

Sheet Prior Results
A1: Test run | B1: Signal | C1: Business / outcome | D1: Result | E1: Detail | F1: What it means for ECS
A2: Test 1 event screen (Oct 6) | B2: SOFR − EFFR | C2: — | D2: PASS | E2: Hit 3/3 events | F2: Usable signal for R3 Option B.
A3: Test 1 event screen (Oct 6) | B3: SOFR − EFFR adjusted | C3: — | D3: PASS | E3: Hit 3/3 events; lower quarter-end alarm rate | F3: Preferred version for R3 Option B.
A4: Test 1 event screen (Oct 6) | B4: 10-yr Treasury abs. change | C4: — | D4: PASS | E4: Hit 2/2 events | F4: FICC signal; not used for ECS.
A5: Test 1 event screen (Oct 6) | B5: Baa spread 20-day widening | C5: — | D5: PASS | E5: Hit 2/2 events | F5: Usable signal for R3 Option A.
A6: Test 1 event screen (Oct 6) | B6: Baa spread level | C6: — | D6: FAIL | E6: Hit 1/2 events | F6: Use the widening version instead.
A7: Test 1 event screen (Oct 6) | B7: VIX | C7: — | D7: FAIL | E7: Hit 1/2 events | F7: Why R1 now proposes an S&P 500 return signal.
A8: Old Test 2 (mixed variables) | B8: VIX | C8: NSCC stress_loss_to_im (a buffer) | D8: FAIL | E8: rho −0.46, wrong direction | F8: The mix-up: a buffer was used as the outcome. v1 fixes this.
A9: Old Test 2 (mixed variables) | B9: SOFR − EFFR | C9: NSCC payment_to_qlr (a buffer) | D9: FAIL (all sample) | E9: rho 0.27; selection sample 0.36 | F9: Same mix-up. v1 moves payment_to_qlr to the vulnerability slot.
A10: Follow-up (exploratory, post-result) | B10: VIX | C10: NSCC im_call_usd | D10: Exploratory | E10: rho 0.27 (n=23) | F10: Weak positive; business reacting in the right direction.
A11: Follow-up (exploratory, post-result) | B11: VIX | C11: NSCC vm_peak_usd | D11: Exploratory | E11: rho 0.33 (n=23) | F11: Weak positive; supports R1 Option B.
A12: Follow-up (exploratory, post-result) | B12: SOFR − EFFR adjusted | C12: NSCC im_call_to_im | D12: Exploratory | E12: rho 0.45 (n=23) | F12: Encouraging for R3 Option B, but already seen.
A13: Follow-up (exploratory, post-result) | B13: SOFR − EFFR adjusted | C13: NSCC vm_peak_to_avg | D13: Exploratory | E13: rho 0.55 (n=23) | F13: Funding stress lines up with VM spikes.
A15: Source: repo results, risk_business_ml/event_vulnerability_tests_2026_10_06/results (event_screen.csv, pqd_lagged_spearman.csv) and feedback_revision_report_2026_10_06/results/response_correlations.csv. 'Exploratory' results were seen before v1 was written, so they don't count as confirmations.

Sheet Data Gaps
A1: Data | B1: Used by | C1: Source | D1: Effort | E1: Notes
A2: S&P 500 daily, 2018 to now (backup R1 signal) | B2: ECS-NSCC-01A/B/C | C2: FRED SP500 | D2: Very easy | E2: Only needed if VIX fails Test 1 again.
A3: PQD 17.2, 17.3 (availability, failures) | B3: ECS-NSCC-02B | C3: Existing PQD xlsx files in repo | D3: Very easy | E3: Same extraction FICC needs for GSD-06.
A4: Financial CP rate (DCPF3M) | B4: ECS-DTC-04 | C4: FRED | D4: Very easy | E4: DTB3/DGS3MO already in database.
A5: Cboe US equity daily volume | B5: ECS-NSCC-02A/B | C5: Cboe market volume summary | D5: Medium | E5: Confirm history back to 2018.
A6: SEC fails-to-deliver | B6: ECS-NSCC-02A, NSCC-05 | C6: SEC FTD data files | D6: Medium | E6: Large files; aggregate to daily totals.
A7: NSCC and DTC monthly fail rates (history) | B7: ECS-NSCC-04, DTC-01 | C7: DTCC Equities by the Numbers | D7: Medium | E7: Only May-2024 and Aug-2026 snapshots so far.
A8: SEC 424B filing counts | B8: ECS-DTC-03 | C8: SEC EDGAR filing index | D8: Medium | E8: Weekly counts.
A9: DTCC Important Notices (outages, extended cutoffs) | B9: ECS-DTC-02A/B | C9: dtcc.com Important Notices | D9: Manual | E9: Needed as the DTC test variable.
A10: DTC Participants Fund / liquidity resources | B10: ECS-DTC-04 (vulnerability candidate) | C10: DTC quarterly financial statements (PDFs in repo) | D10: Manual | E10: Possible DTC buffer since DTC has no PQD.
A11: Historical case evidence | B11: ECS-NSCC-03A, DTC-02A/B, DTC-04 | C11: SEC, DTCC notices, Fed reports, news | D11: Manual | E11: Takes longest; e.g. Jan 2021 NSCC deposit calls.
A12: Scoring rubric for event-type chains | B12: ECS-NSCC-04, NSCC-05, DTC-01 | C12: Model owner | D12: — | E12: Same rubric as FICC event-type chains.

Sheet Open Questions
A1: # | B1: Question | C1: Why it matters | D1: Answer
A2: 1 | B2: Agree that 01A (margin calls) is the R1 primary? | C2: Chosen before testing so we don't pick whichever option passes.
A3: 2 | B3: Decided: keep VIX for R1 for now; S&P 500 daily move is the backup. | C3: VIX failed Test 1 on Oct 6.
A4: 3 | B4: Decided: keep ECS-DTC-03 in ECS for now. | C4: May move to Asset Services later.
A5: 4 | B5: Do PQD 17.2/17.3 report NSCC separately, or DTCC-wide? | C5: Decides whether ECS-NSCC-02B is truly NSCC-specific.
A6: 5 | B6: Use DTC's Participants Fund (from its financial statements) as a DTC vulnerability, or keep DTC as TBD? | C6: Without it, DTC chains score on shock only.
A7: 6 | B7: Which leading signals (margin debt, short interest) are worth collecting now? | C7: They give earlier warning than VIX-style signals.
